README.md
setup.cfg
setup.py
Vigenere_cipher_package2.egg-info/PKG-INFO
Vigenere_cipher_package2.egg-info/SOURCES.txt
Vigenere_cipher_package2.egg-info/dependency_links.txt
Vigenere_cipher_package2.egg-info/top_level.txt
cipherPackage/Cipher.py
cipherPackage/__init__.py