Metadata-Version: 1.0
Name: Vigenere-cipher-package2
Version: 0.4
Summary: An example of Vigenere cipher
Home-page: https://github.com/djankooo/cipherPackage
Author: Jan Kamuda
Author-email: 218202@student.pwr.edu.pl
License: MIT
Platform: UNKNOWN
